README.md
setup.cfg
setup.py
LR_exploration_tf/C_Htd_LR.py
LR_exploration_tf/CyclicLR.py
LR_exploration_tf/HtdLR.py
LR_exploration_tf/__init__.py
LR_scheduler.egg-info/PKG-INFO
LR_scheduler.egg-info/SOURCES.txt
LR_scheduler.egg-info/dependency_links.txt
LR_scheduler.egg-info/not-zip-safe
LR_scheduler.egg-info/top_level.txt