Metadata-Version: 1.0
Name: LR-scheduler
Version: 0.1
Summary: LR_scheduler_basic
Home-page: UNKNOWN
Author: UNKNOWN
Author-email: UNKNOWN
License: UNKNOWN
Platform: UNKNOWN
